[
    {
        "id": 1,
        "title": "News",
        "desc": "Web道場からのお知らせです。記事の追加や更新などの情報をお伝えします",
        "slug": "news"
    },
    {
        "id": 2,
        "title": "Blog",
        "desc": "Web制作に関連するテクニックやお役立ち情報をお届けします",
        "slug": "blog"
    },
    {
        "id": 3,
        "title": "Tutorial",
        "desc": "初めてのウェブサイトを製作して公開までやってみよう",
        "slug": "tutorial"
    },
    {
        "id": 4,
        "title": "HTML/CSS",
        "desc": "HTML/CSSへの理解を深めながら、本格的なサイトを製作しよう",
        "slug": "html-css"
    },
    {
        "id": 5,
        "title": "JavaScript",
        "desc": "JavaScriptでウェブサイトに機能を追加して完成させよう",
        "slug": "javascript"
    }
]